Metadata-Version: 2.1
Name: errandpy
Version: 0.4.3
Summary: an automatical tool for extracting short-range force in NC-AFM data
Home-page: UNKNOWN
Author: ZHUO DIAO
Author-email: enzian0515@gmail.com
License: MIT
Platform: UNKNOWN
